karl/__init__.py
karl/__main__.py
karl/exceptions.py
karl/karl.py
karl/version.py
karl/interfaces/__init__.py
karl/interfaces/cli.py
karl/output/__init__.py
karl/output/exceptions.py
karl/output/folder.py
karl/output/output.py
karl/output/posturl.py
karl/output/stdout.py
karl/sandbox/__init__.py
karl/sandbox/exceptions.py
karl/sandbox/ganache.py
karl/sandbox/sandbox.py
karl/sandbox/vulnerability.py
karl-0.5.2.dist-info/METADATA
karl-0.5.2.dist-info/WHEEL
karl-0.5.2.dist-info/entry_points.txt
karl-0.5.2.dist-info/top_level.txt
karl-0.5.2.dist-info/RECORD
