Metadata-Version: 2.1
Name: karl
Version: 0.5.2
Summary: UNKNOWN
Home-page: UNKNOWN
Author: Daniel Luca
Author-email: daniel.luca@consensys.net
License: MIT
Platform: UNKNOWN
Requires-Dist: mythril (==0.20.6)
Requires-Dist: web3 (==4.9.1)
Requires-Dist: eth-abi (==1.3.0)
Requires-Dist: eth-account (<=0.3.0,>=0.1.0a2)
Requires-Dist: ethereum (>=2.3.2)
Requires-Dist: ethereum-input-decoder (>=0.2.2)
Requires-Dist: eth-hash (>=0.1.0)
Requires-Dist: eth-keyfile (>=0.5.1)
Requires-Dist: eth-keys (>=0.2.0b3)
Requires-Dist: eth-rlp (>=0.1.0)
Requires-Dist: eth-tester (==0.1.0b32)
Requires-Dist: eth-typing (>=2.0.0)
Requires-Dist: eth-utils (>=1.0.1)
